deconveil/__init__.py
deconveil/__version__.py
deconveil/dds.py
deconveil/default_inference.py
deconveil/ds.py
deconveil/grid_search.py
deconveil/inference.py
deconveil/utils_clustering.py
deconveil/utils_fit.py
deconveil/utils_plot.py
deconveil/utils_processing.py
deconveil-0.1.4.dist-info/licenses/LICENSE
deconveil-0.1.4.dist-info/METADATA
deconveil-0.1.4.dist-info/WHEEL
deconveil-0.1.4.dist-info/top_level.txt
deconveil-0.1.4.dist-info/RECORD
