Metadata-Version: 2.4
Name: DeConveil
Version: 0.1.4
Summary: An extension of PyDESeq2/DESeq2 designed to account for genome aneuploidy
Home-page: https://github.com/caravagnalab/DeConveil
Author: Katsiaryna Davydzenka
Author-email: katiasen89@gmail.com
License: MIT
Requires-Python: >=3.10.0
License-File: LICENSE
Requires-Dist: anndata>=0.8.0
Requires-Dist: formulaic>=1.0.2
Requires-Dist: numpy>=1.23.0
Requires-Dist: pandas>=1.4.0
Requires-Dist: scikit-learn>=1.1.0
Requires-Dist: scipy>=1.11.0
Requires-Dist: formulaic-contrasts>=0.2.0
Requires-Dist: matplotlib>=3.6.2
Requires-Dist: seaborn>=0.12.2
Requires-Dist: pydeseq2>=0.4.12
Provides-Extra: dev
Requires-Dist: pytest>=6.2.4; extra == "dev"
Requires-Dist: pre-commit>=2.13.0; extra == "dev"
Requires-Dist: numpydoc; extra == "dev"
Requires-Dist: coverage; extra == "dev"
Requires-Dist: mypy; extra == "dev"
Requires-Dist: pandas-stubs; extra == "dev"
Dynamic: author
Dynamic: author-email
Dynamic: home-page
Dynamic: license
Dynamic: license-file
Dynamic: provides-extra
Dynamic: requires-dist
Dynamic: requires-python
Dynamic: summary
